proxier/__init__.py
proxier/__version__.py
proxier/proxier_requests.py
proxier-0.5.0.dist-info/LICENSE.txt
proxier-0.5.0.dist-info/METADATA
proxier-0.5.0.dist-info/WHEEL
proxier-0.5.0.dist-info/top_level.txt
proxier-0.5.0.dist-info/RECORD
